.pylintrc
LICENSE
MANIFEST.in
README.md
pyproject.toml
tests/test_colors.py
tests/test_jinja.py
tests/test_utils.py
walltheme/__init__.py
walltheme/__main__.py
walltheme/colors.py
walltheme/jinja.py
walltheme/settings.py
walltheme/utils.py
walltheme.egg-info/PKG-INFO
walltheme.egg-info/SOURCES.txt
walltheme.egg-info/dependency_links.txt
walltheme.egg-info/entry_points.txt
walltheme.egg-info/requires.txt
walltheme.egg-info/top_level.txt
walltheme/templates/colors.css.j2
walltheme/templates/colors.j2
walltheme/templates/colors.json.j2
walltheme/templates/colors.scss.j2
walltheme/templates/colors.txt.j2
walltheme/templates/example.j2