Metadata-Version: 2.4
Name: walltheme
Version: 1.0.0
Summary: Generate color themes based on an image's dominant colors
Author-email: Leandro Pata <lmfpata@gmail.com>
License-Expression: MIT
Requires-Python: >=3.10
License-File: LICENSE
Requires-Dist: matplotlib>=3.10.6
Requires-Dist: jinja2>=3.1.6
Requires-Dist: pillow>=11.3.0
Provides-Extra: test
Requires-Dist: pytest>=8.4.2; extra == "test"
Requires-Dist: flake8>=7.3.0; extra == "test"
Dynamic: license-file
